{
  "capacity": 20,
  "slots": [
    {
      "id": "07000000",
      "count": 10
    },
    {
      "id": "07010000",
      "count": 10
    },
    {
      "id": "07020000",
      "count": 10
    },
    {
      "id": "07030000",
      "count": 10
    },
    {
      "id": "07040000",
      "count": 10
    },
    {
      "id": "08010000",
      "count": 1
    },
    {
      "id": "08030000",
      "count": 1
    },
    {
      "id": "08020000",
      "count": 1
    },
    {
      "id": "08010000",
      "count": 1
    },
    {
      "id": "08020000",
      "count": 1
    },
    {
      "id": "08030000",
      "count": 1
    },
    {
      "id": "08000000",
      "count": 1
    },
    {
      "id": "08010000",
      "count": 1
    },
    {
      "id": "08020000",
      "count": 1
    },
    {
      "id": "08030000",
      "count": 1
    }
  ],
  "Key": "total_inv"
}